Your_Fav_DL_Framework/__init__.py
Your_Fav_DL_Framework/activations.py
Your_Fav_DL_Framework/data.py
Your_Fav_DL_Framework/eval.py
Your_Fav_DL_Framework/frame.py
Your_Fav_DL_Framework/loss.py
Your_Fav_DL_Framework/optmizers.py
Your_Fav_DL_Framework-1.0.2.dist-info/METADATA
Your_Fav_DL_Framework-1.0.2.dist-info/WHEEL
Your_Fav_DL_Framework-1.0.2.dist-info/top_level.txt
Your_Fav_DL_Framework-1.0.2.dist-info/RECORD
