Metadata-Version: 2.1
Name: Your-Fav-DL-Framework
Version: 1.0.2
Summary: Deep learning framework
Home-page: https://github.com/pypa/sampleproject
Author: CSE_ASU_2021
Author-email: monairy@icloud.com
License: UNKNOWN
Platform: UNKNOWN
Classifier: Programming Language :: Python :: 3
Classifier: License :: OSI Approved :: MIT License
Classifier: Operating System :: OS Independent
Requires-Python: >=3.
